fast/__init__.py
fast/adber.py
fast/apk.py
fast/compat.py
fast/device.py
fast/env.py
fast/event.py
fast/log.py
fast/mutlitask.py
fast/random_device.py
fast/screen_monitor.py
fast/tac.csv
flashcli-1.3.0.dist-info/METADATA
flashcli-1.3.0.dist-info/WHEEL
flashcli-1.3.0.dist-info/RECORD
