Metadata-Version: 2.1
Name: flashcli
Version: 1.3.0
Summary: flashcli
License: Apache2
Author: electrolyteJ
Author-email: electrolytej@gmail.com
Requires-Python: >=3.9,<4.0
Classifier: License :: Other/Proprietary License
Classifier: Programming Language :: Python :: 3
Classifier: Programming Language :: Python :: 3.9
Classifier: Programming Language :: Python :: 3.10
Classifier: Programming Language :: Python :: 3.11
Requires-Dist: tqdm (>=4.65.0,<5.0.0)
